syncup/__init__.py
syncup/_syncup.py
syncup/py.typed
syncup-0.1.0.dist-info/METADATA
syncup-0.1.0.dist-info/WHEEL
syncup-0.1.0.dist-info/licenses/LICENSE
syncup-0.1.0.dist-info/RECORD
