Metadata-Version: 2.4
Name: syncup
Version: 0.1.0
Summary: Synchronizers for lazy iterators.
Project-URL: homepage, https://github.com/clintval/syncup
Project-URL: repository, https://github.com/clintval/syncup
Project-URL: Bug Tracker, https://github.com/clintval/syncup/issues
Author-email: Clint Valentine <valentine.clint@gmail.com>
License-Expression: MIT
License-File: LICENSE
Classifier: Development Status :: 3 - Alpha
Classifier: Intended Audience :: Developers
Classifier: Intended Audience :: Science/Research
Classifier: License :: OSI Approved :: MIT License
Classifier: Natural Language :: English
Classifier: Operating System :: OS Independent
Classifier: Programming Language :: Python :: 3
Classifier: Programming Language :: Python :: 3.11
Classifier: Programming Language :: Python :: 3.12
Classifier: Programming Language :: Python :: 3.13
Classifier: Typing :: Typed
Requires-Python: >=3.11
